aiogram_store/__init__.py
aiogram_store/__main__.py
aiogram_store/main.py
aiogram_store-0.0.10.dist-info/LICENSE
aiogram_store-0.0.10.dist-info/METADATA
aiogram_store-0.0.10.dist-info/WHEEL
aiogram_store-0.0.10.dist-info/entry_points.txt
aiogram_store-0.0.10.dist-info/top_level.txt
aiogram_store-0.0.10.dist-info/RECORD
