Metadata-Version: 2.1
Name: aiogram-store
Version: 0.0.10
Summary: Python command line example package
Home-page: https://github.com/OGURCHINSKIY/aiogram_store/issues
Author: ogurchik
License: UNKNOWN
Project-URL: Bug Tracker, https://github.com/OGURCHINSKIY/aiogram_store/issues
Platform: UNKNOWN
